[
  {
    "bounds": {
      "northeast": {
        "lat": 53.5597632,
        "lng": 9.9954474
      },
      "southwest": {
        "lat": 53.5519836,
        "lng": 9.9818793
      }
    },
    "copyrights": "Map data \u00a92022 GeoBasis-DE/BKG (\u00a92009), Google",
    "legs": [
      {
        "distance": {
          "text": "1.6 km",
          "value": 1636
        },
        "duration": {
          "text": "7 mins",
          "value": 423
        },
        "end_address": "St. Petersburger Stra\u00dfe / Bei den Kirchh\u00f6fen, 20355 Hamburg, Germany",
        "end_location": {
          "lat": 53.5597124,
          "lng": 9.9818793
        },
        "start_address": "S+U Jungfernstieg / Ballindamm, 20095 Hamburg, Germany",
        "start_location": {
          "lat": 53.5522466,
          "lng": 9.9954474
        },
        "steps": [
          {
            "distance": {
              "text": "65 m",
              "value": 65
            },
            "duration": {
              "text": "1 min",
              "value": 58
            },
            "end_location": {
              "lat": 53.5519836,
              "lng": 9.994589399999999
            },
            "html_instructions": "Head <b>southwest</b> on <b>Ballindamm</b> toward <b>Europa Passage</b><div style=\"font-size:0.9em\">Walk your bicycle</div>",
            "polyline": {
              "points": "qlzeIqf_|@DLPh@Nh@DR@HBR@J?J"
            },
            "start_location": {
              "lat": 53.5522466,
              "lng": 9.9954474
            },
            "travel_mode": "BICYCLING"
          },
          {
            "distance": {
              "text": "9 m",
              "value": 9
            },
            "duration": {
              "text": "1 min",
              "value": 17
            },
            "end_location": {
              "lat": 53.5520649,
              "lng": 9.9946015
            },
            "html_instructions": "Turn <b>right</b> to stay on <b>Ballindamm</b>",
            "maneuver": "turn-right",
            "polyline": {
              "points": "{jzeIea_|@OA"
            },
            "start_location": {
              "lat": 53.5519836,
              "lng": 9.994589399999999
            },
            "travel_mode": "BICYCLING"
          },
          {
            "distance": {
              "text": "0.5 km",
              "value": 521
            },
            "duration": {
              "text": "2 mins",
              "value": 105
            },
            "end_location": {
              "lat": 53.5552733,
              "lng": 9.9889259
            },
            "html_instructions": "Turn <b>left</b> onto <b>Jungfernstieg</b>",
            "maneuver": "turn-left",
            "polyline": {
              "points": "kkzeIga_|@KZQj@ETEFm@~@Yl@U^MVi@`Ay@zAKPw@vAQ\\U\\Uf@MT[r@Q`@KROZIPOX]p@e@|@Sd@GFKRGPIXUnA"
            },
            "start_location": {
              "lat": 53.5520649,
              "lng": 9.9946015
            },
            "travel_mode": "BICYCLING"
          },
          {
            "distance": {
              "text": "0.1 km",
              "value": 102
            },
            "duration": {
              "text": "1 min",
              "value": 20
            },
            "end_location": {
              "lat": 53.5558148,
              "lng": 9.987791
            },
            "html_instructions": "Continue onto <b>G\u00e4nsemarkt</b>",
            "polyline": {
              "points": "m_{eIy}}{@[fBQv@CJCFABABIJCDEDGDCBG@IB"
            },
            "start_location": {
              "lat": 53.5552733,
              "lng": 9.9889259
            },
            "travel_mode": "BICYCLING"
          },
          {
            "distance": {
              "text": "0.3 km",
              "value": 297
            },
            "duration": {
              "text": "1 min",
              "value": 50
            },
            "end_location": {
              "lat": 53.5583044,
              "lng": 9.9893095
            },
            "html_instructions": "Continue onto <b>Dammtorstra\u00dfe</b>",
            "polyline": {
              "points": "yb{eIuv}{@G?IC]Kc@KYIUKSMOKe@_@UUQSQUQQSMOG_@MC?kAa@YKi@_@"
            },
            "start_location": {
              "lat": 53.5558148,
              "lng": 9.987791
            },
            "travel_mode": "BICYCLING"
          },
          {
            "distance": {
              "text": "0.4 km",
              "value": 380
            },
            "duration": {
              "text": "2 mins",
              "value": 97
            },
            "end_location": {
              "lat": 53.5577402,
              "lng": 9.9836841
            },
            "html_instructions": "Turn <b>left</b> onto <b>Gorch-Fock-Wall</b>/<wbr/><b>Ring 1</b>",
            "maneuver": "turn-left",
            "polyline": {
              "points": "kr{eIe`~{@Cz@?XDpCBf@Dz@?PBh@@h@HnBHdCL|CF`ABZF`@@BNbABNPfA"
            },
            "start_location": {
              "lat": 53.5583044,
              "lng": 9.9893095
            },
            "travel_mode": "BICYCLING"
          },
          {
            "distance": {
              "text": "0.2 km",
              "value": 249
            },
            "duration": {
              "text": "1 min",
              "value": 74
            },
            "end_location": {
              "lat": 53.5597632,
              "lng": 9.9820563
            },
            "html_instructions": "Turn <b>right</b> onto <b>Jungiusstra\u00dfe</b>",
            "maneuver": "turn-right",
            "polyline": {
              "points": "{n{eI_}|{@e@ZSLGFGDSPUP[VKHm@`@m@d@EBmAz@OJKHWVSN"
            },
            "start_location": {
              "lat": 53.5577402,
              "lng": 9.9836841
            },
            "travel_mode": "BICYCLING"
          },
          {
            "distance": {
              "text": "13 m",
              "value": 13
            },
            "duration": {
              "text": "1 min",
              "value": 2
            },
            "end_location": {
              "lat": 53.5597124,
              "lng": 9.9818793
            },
            "html_instructions": "Turn <b>left</b> onto <b>b. den Kirchh\u00f6fen</b><div style=\"font-size:0.9em\">Destination will be on the right</div>",
            "maneuver": "turn-left",
            "polyline": {
              "points": "o{{eI{r|{@Hb@"
            },
            "start_location": {
              "lat": 53.5597632,
              "lng": 9.9820563
            },
            "travel_mode": "BICYCLING"
          }
        ],
        "traffic_speed_entry": [],
        "via_waypoint": []
      }
    ],
    "overview_polyline": {
      "points": "qlzeIqf_|@Vv@T|@Ft@OAKZQj@ETs@fAo@lA}BfEuBzDgA~BgAxBy@bBSZQj@q@vD[nAUZSJQBg@O}@Ui@Yu@k@g@i@c@g@c@UiC{@i@_@Cz@DjDL~Cb@|LJ|AHd@RrAPfAe@Z[TGDeAz@mBtA}AfAc@`@SNHb@"
    },
    "summary": "Jungfernstieg",
    "warnings": [
      "Bicycling directions are in beta. Use caution \u2013 This route may contain streets that aren't suited for bicycling."
    ],
    "waypoint_order": []
  }
]