[
  {
    "bounds": {
      "northeast": {
        "lat": 53.5997743,
        "lng": 9.9867416
      },
      "southwest": {
        "lat": 53.58989709999999,
        "lng": 9.943502299999999
      }
    },
    "copyrights": "Map data \u00a92022 GeoBasis-DE/BKG (\u00a92009)",
    "legs": [
      {
        "distance": {
          "text": "3.9 km",
          "value": 3949
        },
        "duration": {
          "text": "14 mins",
          "value": 860
        },
        "end_address": "K\u00fcmmellstra\u00dfe / Robert-Koch-Stra\u00dfe, 20249 Hamburg, Germany",
        "end_location": {
          "lat": 53.5903244,
          "lng": 9.9867416
        },
        "start_address": "U Hagenbecks Tierpark / Koppelstra\u00dfe, 22527 Hamburg, Germany",
        "start_location": {
          "lat": 53.593673,
          "lng": 9.943502299999999
        },
        "steps": [
          {
            "distance": {
              "text": "38 m",
              "value": 38
            },
            "duration": {
              "text": "1 min",
              "value": 6
            },
            "end_location": {
              "lat": 53.59372759999999,
              "lng": 9.944073
            },
            "html_instructions": "Head <b>east</b>",
            "polyline": {
              "points": "mobfI{au{@E_AEq@"
            },
            "start_location": {
              "lat": 53.593673,
              "lng": 9.943502299999999
            },
            "travel_mode": "BICYCLING"
          },
          {
            "distance": {
              "text": "47 m",
              "value": 47
            },
            "duration": {
              "text": "1 min",
              "value": 7
            },
            "end_location": {
              "lat": 53.5941498,
              "lng": 9.9441008
            },
            "html_instructions": "Turn <b>left</b>",
            "maneuver": "turn-left",
            "polyline": {
              "points": "yobfImeu{@IA]AW?SA"
            },
            "start_location": {
              "lat": 53.59372759999999,
              "lng": 9.944073
            },
            "travel_mode": "BICYCLING"
          },
          {
            "distance": {
              "text": "0.3 km",
              "value": 286
            },
            "duration": {
              "text": "1 min",
              "value": 46
            },
            "end_location": {
              "lat": 53.5953878,
              "lng": 9.9477354
            },
            "html_instructions": "Turn <b>right</b>",
            "maneuver": "turn-right",
            "polyline": {
              "points": "mrbfIseu{@Gw@Ci@A]AEA_@Eg@ESOg@?CAIE]C]CSEUK_@Qc@OYKOUa@EICMIa@GUCIM]?AGKKOIKGKGMEKAA"
            },
            "start_location": {
              "lat": 53.5941498,
              "lng": 9.9441008
            },
            "travel_mode": "BICYCLING"
          },
          {
            "distance": {
              "text": "61 m",
              "value": 61
            },
            "duration": {
              "text": "1 min",
              "value": 9
            },
            "end_location": {
              "lat": 53.5950038,
              "lng": 9.9483844
            },
            "html_instructions": "Turn <b>right</b> onto <b>Hugh-Greene-Weg</b>",
            "maneuver": "turn-right",
            "polyline": {
              "points": "ezbfIk|u{@JKNUDIZs@N_@"
            },
            "start_location": {
              "lat": 53.5953878,
              "lng": 9.9477354
            },
            "travel_mode": "BICYCLING"
          },
          {
            "distance": {
              "text": "0.9 km",
              "value": 924
            },
            "duration": {
              "text": "4 mins",
              "value": 223
            },
            "end_location": {
              "lat": 53.5991375,
              "lng": 9.9587086
            },
            "html_instructions": "Turn <b>left</b> onto <b>Julius-Vosseler-Stra\u00dfe</b>",
            "maneuver": "turn-left",
            "polyline": {
              "points": "wwbfIk`v{@Y[OOaAgAACKKCCaA}@g@_@YSOKs@e@a@[mAw@y@i@kAu@[U[YEE[a@KWUg@GSGQCOG]E]CQCYC[E]?ECw@EaAGyAMgDCg@Aa@GwAEiAEeACy@As@C{@?o@?WCiACeAAo@A}@?]"
            },
            "start_location": {
              "lat": 53.5950038,
              "lng": 9.9483844
            },
            "travel_mode": "BICYCLING"
          },
          {
            "distance": {
              "text": "0.4 km",
              "value": 362
            },
            "duration": {
              "text": "1 min",
              "value": 65
            },
            "end_location": {
              "lat": 53.59976589999999,
              "lng": 9.9640433
            },
            "html_instructions": "Continue onto <b>Vogt-Wells-Stra\u00dfe</b>",
            "polyline": {
              "points": "sqcfI}`x{@Ca@Aa@Cs@G_AE_@EUGo@Go@Eq@Gm@AKCa@E_@Ce@Ec@Gy@ESE[Eg@KqAAQAKBW@C?CACEi@?C?Y?s@A[@e@"
            },
            "start_location": {
              "lat": 53.5991375,
              "lng": 9.9587086
            },
            "travel_mode": "BICYCLING"
          },
          {
            "distance": {
              "text": "1.0 km",
              "value": 974
            },
            "duration": {
              "text": "4 mins",
              "value": 216
            },
            "end_location": {
              "lat": 53.5976152,
              "lng": 9.9782244
            },
            "html_instructions": "Continue onto <b>Osterfeldstra\u00dfe</b>",
            "polyline": {
              "points": "qucfIgby{@?EB[@M?KBODQ@C?ABKFWDOHU@G@CDMBGFQDOH_@B_@@Q?UAODi@LmBVaEFaA^_GPgC?CReDNiBFoAFgABc@Dq@Fw@?E@KJiAFu@Bk@FiALsBDo@LiB@KHoALiB@SB]Bg@Dq@@EDq@DY@MHK?AN}@Pw@"
            },
            "start_location": {
              "lat": 53.59976589999999,
              "lng": 9.9640433
            },
            "travel_mode": "BICYCLING"
          },
          {
            "distance": {
              "text": "1.0 km",
              "value": 973
            },
            "duration": {
              "text": "3 mins",
              "value": 200
            },
            "end_location": {
              "lat": 53.58989709999999,
              "lng": 9.9830009
            },
            "html_instructions": "Turn <b>right</b> onto <b>Frickestra\u00dfe</b>",
            "maneuver": "turn-right",
            "polyline": {
              "points": "chcfI{z{{@TPFDz@^F@N@T?hAGtAGtAElAAj@AlCAjBEN?F?@ABA?AHOFOHGDEp@cAzAuB`BaClAeBjCoDHKtAiBx@qALQf@u@HOFKHMHIDENE"
            },
            "start_location": {
              "lat": 53.5976152,
              "lng": 9.9782244
            },
            "travel_mode": "BICYCLING"
          },
          {
            "distance": {
              "text": "0.1 km",
              "value": 107
            },
            "duration": {
              "text": "1 min",
              "value": 64
            },
            "end_location": {
              "lat": 53.5905534,
              "lng": 9.984185199999999
            },
            "html_instructions": "Turn <b>left</b> onto <b>Breitenfelder Str.</b>/<wbr/><b>B5</b><div style=\"font-size:0.9em\">Continue to follow B5</div>",
            "maneuver": "turn-left",
            "polyline": {
              "points": "{wafIwx|{@K[KYSq@Uc@KQQ_@QUOY"
            },
            "start_location": {
              "lat": 53.58989709999999,
              "lng": 9.9830009
            },
            "travel_mode": "BICYCLING"
          },
          {
            "distance": {
              "text": "0.2 km",
              "value": 177
            },
            "duration": {
              "text": "1 min",
              "value": 24
            },
            "end_location": {
              "lat": 53.5903244,
              "lng": 9.9867416
            },
            "html_instructions": "Turn <b>right</b> onto <b>K\u00fcmmellstra\u00dfe</b><div style=\"font-size:0.9em\">Destination will be on the right</div>",
            "maneuver": "turn-right",
            "polyline": {
              "points": "}{afIe`}{@Vu@H]BMBK@KBQ@O@[?E@[Ai@CaACw@AqABm@"
            },
            "start_location": {
              "lat": 53.5905534,
              "lng": 9.984185199999999
            },
            "travel_mode": "BICYCLING"
          }
        ],
        "traffic_speed_entry": [],
        "via_waypoint": []
      }
    ],
    "overview_polyline": {
      "points": "mobfI{au{@KqBg@Ck@AKaBKkBWiASeB]cA[i@[k@Mo@Y_Ae@s@MYHMT_@j@sAmBwBOOiB}A_CaBoFmDa@_@[a@KW]{@Ka@M{@Gk@MwB_@kJUiGIyEIwEA{AEcAKsBKu@]_EOsBM}AKo@UwCBc@Em@?mABcBJ{@Li@j@iBH_@B_@@g@AODi@d@oHx@mMr@gLj@kIdAqPN}BJkAJYN_APw@TPbAd@VBjGUrJKV?DCHQFOHGv@iA|DwFxHkKxBiD`@i@NEK[_@kAeAkBOYVu@Lk@Jy@@gBGyB@_C"
    },
    "summary": "Osterfeldstra\u00dfe",
    "warnings": [
      "Bicycling directions are in beta. Use caution \u2013 This route may contain streets that aren't suited for bicycling."
    ],
    "waypoint_order": []
  }
]