[
  {
    "bounds": {
      "northeast": {
        "lat": 53.5705488,
        "lng": 10.1049508
      },
      "southwest": {
        "lat": 53.5554491,
        "lng": 10.0602911
      }
    },
    "copyrights": "Map data \u00a92022 GeoBasis-DE/BKG (\u00a92009)",
    "legs": [
      {
        "distance": {
          "text": "4.2 km",
          "value": 4210
        },
        "duration": {
          "text": "15 mins",
          "value": 922
        },
        "end_address": "U Rauhes Haus / Horner Weg, 20535 Hamburg, Germany",
        "end_location": {
          "lat": 53.5554624,
          "lng": 10.0669316
        },
        "start_address": "Rodigallee 85, 22043 Hamburg, Germany",
        "start_location": {
          "lat": 53.5705488,
          "lng": 10.104921
        },
        "steps": [
          {
            "distance": {
              "text": "9 m",
              "value": 9
            },
            "duration": {
              "text": "1 min",
              "value": 2
            },
            "end_location": {
              "lat": 53.5704727,
              "lng": 10.1049508
            },
            "html_instructions": "Head <b>south</b> toward <b>Rodigallee</b>",
            "polyline": {
              "points": "}~}eIwrt|@NE"
            },
            "start_location": {
              "lat": 53.5705488,
              "lng": 10.104921
            },
            "travel_mode": "BICYCLING"
          },
          {
            "distance": {
              "text": "0.9 km",
              "value": 866
            },
            "duration": {
              "text": "3 mins",
              "value": 167
            },
            "end_location": {
              "lat": 53.5686664,
              "lng": 10.0922844
            },
            "html_instructions": "Turn <b>right</b> onto <b>Rodigallee</b>",
            "maneuver": "turn-right",
            "polyline": {
              "points": "m~}eI}rt|@B^?B@@HL@NDz@HtAXrD?FVtC^|D@H?@d@fERbBP|A`@dDBZLdA@JTvBH`ADf@LdAHr@JrAHdAFhAF~ADt@DzA?d@@l@?z@ArC"
            },
            "start_location": {
              "lat": 53.5704727,
              "lng": 10.1049508
            },
            "travel_mode": "BICYCLING"
          },
          {
            "distance": {
              "text": "0.4 km",
              "value": 404
            },
            "duration": {
              "text": "1 min",
              "value": 61
            },
            "end_location": {
              "lat": 53.5689167,
              "lng": 10.0861746
            },
            "html_instructions": "Continue onto <b>J\u00fcthornstra\u00dfe</b>",
            "polyline": {
              "points": "es}eIwcr|@E~BAp@EzCAbAKtGAl@G|DCpB?PGlD"
            },
            "start_location": {
              "lat": 53.5686664,
              "lng": 10.0922844
            },
            "travel_mode": "BICYCLING"
          },
          {
            "distance": {
              "text": "1.4 km",
              "value": 1449
            },
            "duration": {
              "text": "6 mins",
              "value": 372
            },
            "end_location": {
              "lat": 53.5630442,
              "lng": 10.0670015
            },
            "html_instructions": "Turn <b>left</b> to stay on <b>J\u00fcthornstra\u00dfe</b>",
            "maneuver": "turn-left",
            "polyline": {
              "points": "wt}eIq}p|@HFDFBBDFFPBFBFBPFZVtB@P@BFj@?B`@zCVrBBRZbCZdCJ|@?H@J?B?F|@fH\\vCb@`DD^?BLlADXCR?B?HDd@D`@Ht@@LLhAF`@Lz@J|@Lv@@@HPDTTdAXbAHNLTb@v@PZ@B^n@FPFNDJZp@j@zAV|@Nf@Rt@BNd@tBRz@ZjAd@vAvBbGJXLXN`@FRRj@@BPn@Nj@R|@DRD\\"
            },
            "start_location": {
              "lat": 53.5689167,
              "lng": 10.0861746
            },
            "travel_mode": "BICYCLING"
          },
          {
            "distance": {
              "text": "0.2 km",
              "value": 211
            },
            "duration": {
              "text": "1 min",
              "value": 85
            },
            "end_location": {
              "lat": 53.5624608,
              "lng": 10.0640065
            },
            "html_instructions": "Slight <b>left</b> onto <b>Hammer Str.</b>",
            "maneuver": "turn-slight-left",
            "polyline": {
              "points": "_p|eIwem|@BNR`ANt@@DJf@@FF\\?B?B?BCLHf@RlBDp@?J@D?BDv@@JH|@"
            },
            "start_location": {
              "lat": 53.5630442,
              "lng": 10.0670015
            },
            "travel_mode": "BICYCLING"
          },
          {
            "distance": {
              "text": "0.2 km",
              "value": 224
            },
            "duration": {
              "text": "1 min",
              "value": 41
            },
            "end_location": {
              "lat": 53.5620832,
              "lng": 10.0606797
            },
            "html_instructions": "Continue onto <b>Quellenweg</b>",
            "polyline": {
              "points": "kl|eIasl|@@h@Dz@DvANrDb@xEHlA"
            },
            "start_location": {
              "lat": 53.5624608,
              "lng": 10.0640065
            },
            "travel_mode": "BICYCLING"
          },
          {
            "distance": {
              "text": "0.2 km",
              "value": 248
            },
            "duration": {
              "text": "1 min",
              "value": 56
            },
            "end_location": {
              "lat": 53.5602433,
              "lng": 10.0614128
            },
            "html_instructions": "At the roundabout, take the <b>3rd</b> exit onto <b>Caspar-Voght-Stra\u00dfe</b>",
            "maneuver": "roundabout-right",
            "polyline": {
              "points": "_j|eIg~k|@A@?@?@A??@?@?@A@?@?@?@A@?@?@?@?@?@?@?@?@A@@@?@?@?@@@?@?@@@?@?@@??@?@@??@@@?@@??@@??@@??@@?@??@@?@?@?@A@?@??A@?@??A@??A@??A@??A@A?A?A@A?A?A@A?A?A@A?Aj@s@POf@_@JIHGr@[VG`@Kd@GZEXI"
            },
            "start_location": {
              "lat": 53.5620832,
              "lng": 10.0606797
            },
            "travel_mode": "BICYCLING"
          },
          {
            "distance": {
              "text": "0.3 km",
              "value": 261
            },
            "duration": {
              "text": "1 min",
              "value": 43
            },
            "end_location": {
              "lat": 53.5597428,
              "lng": 10.0652729
            },
            "html_instructions": "Turn <b>left</b> onto <b>Sievekingsallee</b>",
            "maneuver": "turn-left",
            "polyline": {
              "points": "o~{eIybl|@Ba@NuBBg@HiABa@RwCFcAFo@Dw@Di@LiB"
            },
            "start_location": {
              "lat": 53.5602433,
              "lng": 10.0614128
            },
            "travel_mode": "BICYCLING"
          },
          {
            "distance": {
              "text": "0.5 km",
              "value": 479
            },
            "duration": {
              "text": "1 min",
              "value": 84
            },
            "end_location": {
              "lat": 53.555457,
              "lng": 10.0660366
            },
            "html_instructions": "Turn <b>right</b> onto <b>Mettlerkampsweg</b>",
            "maneuver": "turn-right",
            "polyline": {
              "points": "k{{eI}zl|@d@CzBUfD_@rCWp@IdAKj@G\\IlAOf@G`AG"
            },
            "start_location": {
              "lat": 53.5597428,
              "lng": 10.0652729
            },
            "travel_mode": "BICYCLING"
          },
          {
            "distance": {
              "text": "59 m",
              "value": 59
            },
            "duration": {
              "text": "1 min",
              "value": 11
            },
            "end_location": {
              "lat": 53.5554624,
              "lng": 10.0669316
            },
            "html_instructions": "Turn <b>left</b> onto <b>Horner Weg</b><div style=\"font-size:0.9em\">Destination will be on the left</div>",
            "maneuver": "turn-left",
            "polyline": {
              "points": "s`{eIw_m|@@m@?eAAu@?G"
            },
            "start_location": {
              "lat": 53.555457,
              "lng": 10.0660366
            },
            "travel_mode": "BICYCLING"
          }
        ],
        "traffic_speed_entry": [],
        "via_waypoint": []
      }
    ],
    "overview_polyline": {
      "points": "}~}eIwrt|@NEB^@DHL@NNpCXzDv@rIz@vHdAdJf@lFVxBTxCNhDJpC?bHOpKYrRG~DNNTd@FX^pCJdAxAfLf@bE@TzAjMh@`ELpADXCR?LVjCn@dFNx@HPDTn@hCVd@vAfCp@~AbAxCb@|Ah@dCn@fC|CzIXr@l@dB`@zAXpAHl@b@vBVrACX\\tCD|@HlAJfBJrCNrDb@xEFnAAB?DCJ?JBTHNHBJEHOBK|@cAr@i@|@c@x@S`AMXIBa@R}CLkBh@cIRsC`DYzHw@vBUhAQtBW`AG@m@A{B?G"
    },
    "summary": "J\u00fcthornstra\u00dfe",
    "warnings": [
      "Bicycling directions are in beta. Use caution \u2013 This route may contain streets that aren't suited for bicycling."
    ],
    "waypoint_order": []
  }
]