[
  {
    "bounds": {
      "northeast": {
        "lat": 53.6487811,
        "lng": 10.0162479
      },
      "southwest": {
        "lat": 53.5884609,
        "lng": 9.9852016
      }
    },
    "copyrights": "Map data \u00a92022 GeoBasis-DE/BKG (\u00a92009)",
    "legs": [
      {
        "distance": {
          "text": "8.1 km",
          "value": 8108
        },
        "duration": {
          "text": "26 mins",
          "value": 1584
        },
        "end_address": "U Kellinghusenstra\u00dfe / Loogeplatz, 20249 Hamburg, Germany",
        "end_location": {
          "lat": 53.5884609,
          "lng": 9.9914303
        },
        "start_address": "U Langenhorn Markt / Tangstedter Landstra\u00dfe, 22415 Hamburg, Germany",
        "start_location": {
          "lat": 53.6487811,
          "lng": 10.0162479
        },
        "steps": [
          {
            "distance": {
              "text": "0.4 km",
              "value": 391
            },
            "duration": {
              "text": "1 min",
              "value": 56
            },
            "end_location": {
              "lat": 53.6461696,
              "lng": 10.0124694
            },
            "html_instructions": "Head <b>southwest</b> on <b>Tangstedter Landstra\u00dfe</b> toward <b>Tannenweg</b>",
            "polyline": {
              "points": "{gmfIqhc|@D@B@BBrDfDd@f@RRNFRZLTRb@p@lB~@`Cr@fB@BVt@FV"
            },
            "start_location": {
              "lat": 53.6487811,
              "lng": 10.0162479
            },
            "travel_mode": "BICYCLING"
          },
          {
            "distance": {
              "text": "0.8 km",
              "value": 790
            },
            "duration": {
              "text": "3 mins",
              "value": 203
            },
            "end_location": {
              "lat": 53.6392296,
              "lng": 10.0135554
            },
            "html_instructions": "Turn <b>left</b> onto <b>Langenhorner Chaussee</b>",
            "maneuver": "turn-left",
            "polyline": {
              "points": "qwlfI}pb|@PQLKNILGNEPGXGhAS|@MNCPE\\ED?b@?N?vALtBPTANCD@|BTXDjAPtAPp@@\\?R?\\KRKPI`@ULIZOVKL?B?BAZMh@[VONIj@["
            },
            "start_location": {
              "lat": 53.6461696,
              "lng": 10.0124694
            },
            "travel_mode": "BICYCLING"
          },
          {
            "distance": {
              "text": "0.3 km",
              "value": 277
            },
            "duration": {
              "text": "1 min",
              "value": 42
            },
            "end_location": {
              "lat": 53.6379874,
              "lng": 10.009927
            },
            "html_instructions": "Turn <b>right</b> onto <b>Am Raakmoorgraben</b>",
            "maneuver": "turn-right",
            "polyline": {
              "points": "elkfIwwb|@BR@H@DDNb@`BHZZlAZvAp@hC?Bv@zCXrA"
            },
            "start_location": {
              "lat": 53.6392296,
              "lng": 10.0135554
            },
            "travel_mode": "BICYCLING"
          },
          {
            "distance": {
              "text": "1.2 km",
              "value": 1185
            },
            "duration": {
              "text": "4 mins",
              "value": 213
            },
            "end_location": {
              "lat": 53.6275316,
              "lng": 10.0093067
            },
            "html_instructions": "Turn <b>left</b>",
            "maneuver": "turn-left",
            "polyline": {
              "points": "mdkfIaab|@LIVSPOHGLIJCJEXC\\CJ?B?T@\\BN@@?R@RAd@Eb@Eh@Cd@AzDDjBCFBd@FV@P@p@HJ@B@B?FAB?FCHELKL@P@PF`@LNFZPB@NHLHVJ`@LLBN?`@B`@?VCX@NN~@j@PBT?ZA@?ZBD@VFJD^XHEPBHBNDb@NXD^@\\?F?l@?|@Cp@?n@CRCTEb@KF?F?H@LCLAHC"
            },
            "start_location": {
              "lat": 53.6379874,
              "lng": 10.009927
            },
            "travel_mode": "BICYCLING"
          },
          {
            "distance": {
              "text": "77 m",
              "value": 77
            },
            "duration": {
              "text": "1 min",
              "value": 41
            },
            "end_location": {
              "lat": 53.6275404,
              "lng": 10.0082123
            },
            "html_instructions": "Turn <b>right</b> onto the ramp to <b>Flughafenstr.</b>",
            "maneuver": "ramp-right",
            "polyline": {
              "points": "acifIe}a|@@R?J@\\C@C@CDBP?F?F?r@@f@?T"
            },
            "start_location": {
              "lat": 53.6275316,
              "lng": 10.0093067
            },
            "travel_mode": "BICYCLING"
          },
          {
            "distance": {
              "text": "0.4 km",
              "value": 448
            },
            "duration": {
              "text": "1 min",
              "value": 70
            },
            "end_location": {
              "lat": 53.6238621,
              "lng": 10.010539
            },
            "html_instructions": "Turn <b>left</b> onto <b>Flughafenstr.</b>",
            "maneuver": "turn-left",
            "polyline": {
              "points": "ccifIiva|@`@@p@C~@Ib@IZGdA]b@OzAu@v@g@DGR_@HGJIj@_@f@]VSp@q@~@iB"
            },
            "start_location": {
              "lat": 53.6275404,
              "lng": 10.0082123
            },
            "travel_mode": "BICYCLING"
          },
          {
            "distance": {
              "text": "71 m",
              "value": 71
            },
            "duration": {
              "text": "1 min",
              "value": 24
            },
            "end_location": {
              "lat": 53.6233562,
              "lng": 10.0111907
            },
            "html_instructions": "Continue onto <b>B433</b>",
            "polyline": {
              "points": "clhfI{db|@Zm@d@k@`@g@"
            },
            "start_location": {
              "lat": 53.6238621,
              "lng": 10.010539
            },
            "travel_mode": "BICYCLING"
          },
          {
            "distance": {
              "text": "2.9 km",
              "value": 2870
            },
            "duration": {
              "text": "8 mins",
              "value": 509
            },
            "end_location": {
              "lat": 53.60277620000001,
              "lng": 9.9860809
            },
            "html_instructions": "Turn <b>right</b> onto <b>Alsterkrugchaussee</b>/<wbr/><b>Zeppelinstra\u00dfe</b>/<wbr/><b>B433</b><div style=\"font-size:0.9em\">Continue to follow B433</div>",
            "maneuver": "turn-right",
            "polyline": {
              "points": "_ihfI}hb|@n@TB@pAb@VFVHd@JF@VDRD@@XCFD^HRFJDLDRFXJj@PJDNDf@PD@PHNDTHLFZLf@V^T@@XRZXZXX\\LLn@|@?@`@n@?@`@r@BD^r@DJh@~@zAlCFTFRHRTl@JXNVNXHJRZBD@@B@B@JNDFXb@j@bAb@z@T`@^r@BDR^Zl@DHz@|AbAlBJRh@`AJPj@hABDNd@HPXf@PXZl@NTx@xAfApBZf@NX^p@lAvBFHb@x@DFDHf@z@NRNXbAdBV`@r@jAl@fA\\l@h@z@Xh@f@v@f@x@NRFJf@v@R\\dAvA\\f@PTp@~@PTn@t@f@r@nAdB~AvB|@pAV^Xb@d@p@vAvBR\\RXNRFHPXV\\Zb@`@f@Z`@`@f@LNTV~@fALLPPFF^\\PNTRLJ\\Xp@p@Z\\X\\`@d@r@bABBR\\"
            },
            "start_location": {
              "lat": 53.6233562,
              "lng": 10.0111907
            },
            "travel_mode": "BICYCLING"
          },
          {
            "distance": {
              "text": "58 m",
              "value": 58
            },
            "duration": {
              "text": "1 min",
              "value": 7
            },
            "end_location": {
              "lat": 53.6027821,
              "lng": 9.9852016
            },
            "html_instructions": "Turn <b>right</b>",
            "maneuver": "turn-right",
            "polyline": {
              "points": "khdfI_l}{@Cd@?N?^?V?X@N@V"
            },
            "start_location": {
              "lat": 53.60277620000001,
              "lng": 9.9860809
            },
            "travel_mode": "BICYCLING"
          },
          {
            "distance": {
              "text": "0.1 km",
              "value": 116
            },
            "duration": {
              "text": "1 min",
              "value": 45
            },
            "end_location": {
              "lat": 53.6022463,
              "lng": 9.9866417
            },
            "html_instructions": "Turn <b>left</b>",
            "maneuver": "turn-left",
            "polyline": {
              "points": "khdfIof}{@`@i@Lm@BGH_@Po@@CRu@BY?["
            },
            "start_location": {
              "lat": 53.6027821,
              "lng": 9.9852016
            },
            "travel_mode": "BICYCLING"
          },
          {
            "distance": {
              "text": "0.6 km",
              "value": 595
            },
            "duration": {
              "text": "2 mins",
              "value": 107
            },
            "end_location": {
              "lat": 53.59729859999999,
              "lng": 9.9889868
            },
            "html_instructions": "Slight <b>right</b>",
            "maneuver": "turn-slight-right",
            "polyline": {
              "points": "aedfIoo}{@ZkAXm@FE@?r@_@`@M`@KLE^MPKDCRMDCDEHGTS^Y?Ab@a@f@i@PQDELEb@ELAFAj@Sl@Md@K`A?n@BV@J@dADf@Db@C`@IHK"
            },
            "start_location": {
              "lat": 53.6022463,
              "lng": 9.9866417
            },
            "travel_mode": "BICYCLING"
          },
          {
            "distance": {
              "text": "0.3 km",
              "value": 348
            },
            "duration": {
              "text": "1 min",
              "value": 58
            },
            "end_location": {
              "lat": 53.59438669999999,
              "lng": 9.988235699999999
            },
            "html_instructions": "Turn <b>right</b> onto <b>Eppendorfer Landstra\u00dfe</b>",
            "maneuver": "turn-right",
            "polyline": {
              "points": "cfcfIe~}{@LPJPLTBDRXLPd@`@XTLHRLp@Ph@LJ@P@PAb@IFALG\\OJETKFARCF@D?P?f@?X@PO"
            },
            "start_location": {
              "lat": 53.59729859999999,
              "lng": 9.9889868
            },
            "travel_mode": "BICYCLING"
          },
          {
            "distance": {
              "text": "50 m",
              "value": 50
            },
            "duration": {
              "text": "1 min",
              "value": 43
            },
            "end_location": {
              "lat": 53.5941336,
              "lng": 9.9888531
            },
            "html_instructions": "Slight <b>left</b> to stay on <b>Eppendorfer Landstra\u00dfe</b>",
            "maneuver": "turn-slight-left",
            "polyline": {
              "points": "}sbfIoy}{@^sABE@ELY"
            },
            "start_location": {
              "lat": 53.59438669999999,
              "lng": 9.988235699999999
            },
            "travel_mode": "BICYCLING"
          },
          {
            "distance": {
              "text": "0.1 km",
              "value": 123
            },
            "duration": {
              "text": "1 min",
              "value": 22
            },
            "end_location": {
              "lat": 53.59309090000001,
              "lng": 9.989239999999999
            },
            "html_instructions": "Continue onto <b>Eppendorfer Marktpl.</b>",
            "polyline": {
              "points": "irbfIi}}{@HQHKFGFEHADAJAh@?f@AL?DAH?DAJELO"
            },
            "start_location": {
              "lat": 53.5941336,
              "lng": 9.9888531
            },
            "travel_mode": "BICYCLING"
          },
          {
            "distance": {
              "text": "0.2 km",
              "value": 239
            },
            "duration": {
              "text": "1 min",
              "value": 55
            },
            "end_location": {
              "lat": 53.5925824,
              "lng": 9.9926417
            },
            "html_instructions": "Turn <b>left</b> onto <b>Heinickestra\u00dfe</b>/<wbr/><b>B5</b><div style=\"font-size:0.9em\">Continue to follow B5</div>",
            "maneuver": "turn-left",
            "polyline": {
              "points": "ykbfIw_~{@GS?_@@i@@eBB{@?O@QJu@Z_BTaAXgAFa@BQ@S?KAQ"
            },
            "start_location": {
              "lat": 53.59309090000001,
              "lng": 9.989239999999999
            },
            "travel_mode": "BICYCLING"
          },
          {
            "distance": {
              "text": "0.5 km",
              "value": 454
            },
            "duration": {
              "text": "1 min",
              "value": 86
            },
            "end_location": {
              "lat": 53.5885958,
              "lng": 9.9915153
            },
            "html_instructions": "Turn <b>right</b> onto <b>Kellinghusenstra\u00dfe</b>",
            "maneuver": "turn-right",
            "polyline": {
              "points": "shbfI_u~{@@E@?@?NBhAL@?@AFEPFXFBD?@VFd@H~@VXH|A^xA`@h@NNBF?NLHBFBNDDBHBRFFBT@B?F?PBP?D?D@D?^@@@FAH@BA"
            },
            "start_location": {
              "lat": 53.5925824,
              "lng": 9.9926417
            },
            "travel_mode": "BICYCLING"
          },
          {
            "distance": {
              "text": "16 m",
              "value": 16
            },
            "duration": {
              "text": "1 min",
              "value": 3
            },
            "end_location": {
              "lat": 53.5884609,
              "lng": 9.9914303
            },
            "html_instructions": "Slight <b>right</b> onto <b>Loogepl.</b><div style=\"font-size:0.9em\">Destination will be on the right</div>",
            "maneuver": "turn-slight-right",
            "polyline": {
              "points": "woafI_n~{@NJJD"
            },
            "start_location": {
              "lat": 53.5885958,
              "lng": 9.9915153
            },
            "travel_mode": "BICYCLING"
          }
        ],
        "traffic_speed_entry": [],
        "via_waypoint": []
      }
    ],
    "overview_polyline": {
      "points": "{gmfIqhc|@HBvDjDx@z@NFRZ`@x@pBnFt@jB^lA^]\\Q`@MbB[|B]h@?fBLtBPTATAvCZ`Db@nA@R?\\Kd@Un@_@r@[P?^O`Ak@z@e@D\\t@rChBrHpAnFd@]ZWXMd@Ih@CfAFT@x@GlAI`FBrB?|@HrANVEVQ^Br@Tj@Xx@`@n@Pp@Bx@CX@NN~@j@PBp@A\\B\\Hj@^HEPBXH|@TrB@nBCbAGx@QN?VAVE@^@\\C@GFBX@xBrAAbBS`Be@~BeA|@o@R_@HGv@i@~@q@p@q@~@iBZm@d@k@`@g@n@TtAd@|A^j@JZAfA\\fBj@nC`AbAd@`@Vt@l@t@v@|@jA`@p@dAnBn@jAzAlCFTPf@`@fA|@xALJPVdAfB|AvCvFjKn@nAXv@vAdCfIzNbFnInCzEfBpC~CtEdC`DtGbJnDlFfDxE`BpBfBnBtAlAnAjAt@z@tAhBV`@ClB@h@@V`@i@Pu@H_@Rs@VoA?[ZkAXm@FE@?tAm@n@Qp@Yd@[~@w@bBcBfAOxAa@d@K`A?fADpAFf@Db@C`@IHKXb@PZ`@j@~@v@`@VzA^\\Bt@K~@_@\\MRCF@V?`A@PO^sADKVk@PSPGPCdBCNAXUGS?_@@i@FcEJu@Z_Bn@iCJs@@_@?WB?|ANFEPFXFBDVHdB`@vBh@bCp@VBXPf@PZJX@p@Bl@DP?RHJD"
    },
    "summary": "B433",
    "warnings": [
      "Bicycling directions are in beta. Use caution \u2013 This route may contain streets that aren't suited for bicycling."
    ],
    "waypoint_order": []
  }
]